CHANGELOG.rst
COPYING
COPYING.LESSER
MANIFEST.in
README.rst
setup.py
statscache_plugins/__init__.py
statscache_plugins.egg-info/PKG-INFO
statscache_plugins.egg-info/SOURCES.txt
statscache_plugins.egg-info/dependency_links.txt
statscache_plugins.egg-info/entry_points.txt
statscache_plugins.egg-info/not-zip-safe
statscache_plugins.egg-info/pbr.json
statscache_plugins.egg-info/requires.txt
statscache_plugins.egg-info/top_level.txt
statscache_plugins/releng/__init__.py
statscache_plugins/releng/plugins/__init__.py
statscache_plugins/releng/plugins/amis.py
statscache_plugins/releng/plugins/artifacts.py
statscache_plugins/releng/plugins/compose.py
statscache_plugins/releng/plugins/updates.py
statscache_plugins/volume/__init__.py
statscache_plugins/volume/by_category.py
statscache_plugins/volume/by_package.py
statscache_plugins/volume/by_topic.py
statscache_plugins/volume/by_user.py
statscache_plugins/volume/simple.py
statscache_plugins/volume/utils.py
tests/__init__.py
tests/test_releng.py
tests/test_volume.py