Metadata-Version: 1.1
Name: statscache-plugins
Version: 0.0.2
Summary: Plugins for statscache, the fedmsg statistics daemon
Home-page: https://github.com/fedora-infra/statscache_plugins/
Author: Ralph Bean
Author-email: rbean@redhat.com
License: LGPLv2+
Download-URL: https://pypi.python.org/pypi/statscache_plugins/
Platform: UNKNOWN
Classifier: Environment :: Web Environment
Classifier: Topic :: Software Development :: Libraries :: Python Modules
Classifier: Intended Audience :: Developers
Classifier: Programming Language :: Python
